{"v":"5.12.1","fr":60,"ip":0,"op":112,"w":512,"h":512,"nm":"Settings","ddd":0,"assets":[],"layers":[{"ddd":0,"ind":1,"ty":4,"nm":"Shape Layer 2","sr":1,"ks":{"o":{"a":0,"k":100,"ix":11},"r":{"a":0,"k":0,"ix":10},"p":{"a":0,"k":[256,181.5,0],"ix":2,"l":2},"a":{"a":0,"k":[0.5,-74,0],"ix":1,"l":2},"s":{"a":0,"k":[100,100,100],"ix":6,"l":2}},"ao":0,"shapes":[{"ty":"gr","it":[{"ty":"gr","it":[{"d":1,"ty":"el","s":{"a":1,"k":[{"i":{"x":[0.667,0.667],"y":[1,1]},"o":{"x":[0.333,0.333],"y":[0,0]},"t":67,"s":[114.657,114.657]},{"t":79,"s":[171.657,171.657]}],"ix":2},"p":{"a":0,"k":[0,0],"ix":3},"nm":"Ellipse Path 1","mn":"ADBE Vector Shape - Ellipse","hd":false},{"ind":1,"ty":"sh","ix":2,"ks":{"a":1,"k":[{"i":{"x":0.667,"y":1},"o":{"x":0.333,"y":0},"t":67,"s":[{"i":[[23.981,0],[0,-23.981],[-23.981,0],[0,23.981]],"o":[[-23.981,0],[0,23.981],[23.981,0],[0,-23.981]],"v":[[0,-43.922],[-43.422,-0.5],[0,42.922],[43.422,-0.5]],"c":true}]},{"t":79,"s":[{"i":[[0,0],[0,0],[0,0],[0,0]],"o":[[0,0],[0,0],[0,0],[0,0]],"v":[[0.5,-85.5],[0.5,-85.5],[0.5,-85.5],[0.5,-85.5]],"c":true}]}],"ix":2},"nm":"Path 1","mn":"ADBE Vector Shape - Group","hd":false},{"ty":"tr","p":{"a":1,"k":[{"i":{"x":0.695,"y":0.543},"o":{"x":0.381,"y":0.176},"t":0,"s":[-0.037,43.123],"to":[0,0],"ti":[0,0]},{"i":{"x":0.655,"y":0.646},"o":{"x":0.331,"y":0.303},"t":5.393,"s":[-28.037,47.123],"to":[0,0],"ti":[0,0]},{"i":{"x":0.61,"y":0.687},"o":{"x":0.293,"y":0.336},"t":8.678,"s":[-0.037,43.123],"to":[0,0],"ti":[0,0]},{"i":{"x":0.532,"y":1},"o":{"x":0.228,"y":0.562},"t":14.16,"s":[42.233,42.939],"to":[0,0],"ti":[0,0]},{"i":{"x":0,"y":1},"o":{"x":0.068,"y":0},"t":31,"s":[-0.037,43.123],"to":[0,0],"ti":[0,0]},{"i":{"x":0.194,"y":1},"o":{"x":0.979,"y":0},"t":48,"s":[-0.037,101.123],"to":[0,0],"ti":[0,0]},{"i":{"x":0.361,"y":1},"o":{"x":0.802,"y":0},"t":67,"s":[-0.037,-51.877],"to":[0,0],"ti":[0,0]},{"i":{"x":0.022,"y":1},"o":{"x":0.392,"y":0},"t":84,"s":[-0.037,84.123],"to":[0,0],"ti":[0,0]},{"t":93,"s":[-0.037,43.123]}],"ix":2},"a":{"a":0,"k":[-0.037,43.123],"ix":1},"s":{"a":1,"k":[{"i":{"x":[0,0],"y":[1,1]},"o":{"x":[0.068,0.068],"y":[0,0]},"t":31,"s":[100,100]},{"i":{"x":[0.194,0.194],"y":[1,1]},"o":{"x":[0.979,0.979],"y":[0,0]},"t":48,"s":[132,67]},{"i":{"x":[0.361,0.361],"y":[1,1]},"o":{"x":[0.802,0.802],"y":[0,0]},"t":67,"s":[82,128]},{"i":{"x":[0.022,0.022],"y":[1,1]},"o":{"x":[0.392,0.392],"y":[0,0]},"t":84,"s":[120,80]},{"t":93,"s":[100,100]}],"ix":3},"r":{"a":0,"k":0,"ix":6},"o":{"a":0,"k":100,"ix":7},"sk":{"a":0,"k":0,"ix":4},"sa":{"a":0,"k":0,"ix":5},"nm":"Transform"}],"nm":"Group 1","np":2,"cix":2,"bm":0,"ix":1,"mn":"ADBE Vector Group","hd":false},{"ty":"st","c":{"a":0,"k":[0.419607843137,0.427450980392,0.501960784314,1],"ix":3},"o":{"a":0,"k":100,"ix":4},"w":{"a":0,"k":0,"ix":5},"lc":1,"lj":1,"ml":4,"bm":0,"nm":"Stroke 1","mn":"ADBE Vector Graphic - Stroke","hd":false},{"ty":"fl","c":{"a":0,"k":[0.188235309077,0.20000001496,0.270588235294,1],"ix":4},"o":{"a":0,"k":100,"ix":5},"r":1,"bm":0,"nm":"Fill 1","mn":"ADBE Vector Graphic - Fill","hd":false},{"ty":"tr","p":{"a":1,"k":[{"i":{"x":0.667,"y":1},"o":{"x":0.333,"y":0},"t":67,"s":[0.5,-74],"to":[0,0],"ti":[0,0]},{"t":79,"s":[0.5,-85]}],"ix":2},"a":{"a":0,"k":[0,0],"ix":1},"s":{"a":0,"k":[100,100],"ix":3},"r":{"a":0,"k":0,"ix":6},"o":{"a":0,"k":100,"ix":7},"sk":{"a":0,"k":0,"ix":4},"sa":{"a":0,"k":0,"ix":5},"nm":"Transform"}],"nm":"Ellipse 1","np":3,"cix":2,"bm":0,"ix":1,"mn":"ADBE Vector Group","hd":false},{"ty":"gr","it":[{"ind":0,"ty":"sh","ix":1,"ks":{"a":1,"k":[{"i":{"x":0.667,"y":1},"o":{"x":0.333,"y":0},"t":67,"s":[{"i":[[53,0.25],[13,-7.5],[0.5,-13.5],[0,0],[0,0],[0,5.875],[19.062,11.25]],"o":[[-51.752,-0.244],[-13,7.5],[-0.5,13.5],[0,0],[0,0],[0,-5.875],[-15.599,-9.206]],"v":[[1.75,38.25],[-118,67],[-142.75,100.75],[-142.625,133.25],[143.375,133.375],[143.375,102.875],[120.75,68.75]],"c":true}]},{"t":79,"s":[{"i":[[63.147,0.391],[14.244,-13.203],[0,-23.778],[0,0],[0,0],[0,9.179],[24.957,20.967]],"o":[[-61.66,-0.381],[-22.334,20.701],[0,21.1],[0,0],[0,0],[0,-13.598],[-17.993,-15.117]],"v":[[0.511,21.631],[-146.166,61.549],[-169.904,120.028],[-170.005,171.305],[171.5,171],[171.5,123.348],[147.793,62.033]],"c":true}]}],"ix":2},"nm":"Path 2","mn":"ADBE Vector Shape - Group","hd":false},{"ind":1,"ty":"sh","ix":2,"ks":{"a":1,"k":[{"i":{"x":0.667,"y":1},"o":{"x":0.333,"y":0},"t":67,"s":[{"i":[[-12.789,0.12],[-25.573,-5.212],[-17.5,-8],[0,0],[0,0],[0,0],[0,0.75],[-5.75,3.25],[-18.25,4.25]],"o":[[13.375,-0.125],[26.375,5.375],[16.765,7.664],[0,0],[0,0],[0,0],[6.75,-18],[5.75,-3.25],[18.25,-4.25]],"v":[[0.625,54.125],[52,59.875],[108.125,79.125],[128.375,101],[128.5,117.625],[-127.5,117.875],[-127.25,100.125],[-95,73.5],[-47.125,58.75]],"c":true}]},{"t":79,"s":[{"i":[[0,0],[0,0],[0,0],[0,0],[0,0],[0,0],[0,0],[0,0],[0,0]],"o":[[0,0],[0,0],[0,0],[0,0],[0,0],[0,0],[0,0],[0,0],[0,0]],"v":[[0.5,85.938],[0.5,85.938],[0.5,85.938],[0.5,85.938],[0.5,85.938],[0.5,85.938],[0.5,85.938],[0.5,85.938],[0.5,85.938]],"c":true}]}],"ix":2},"nm":"Path 1","mn":"ADBE Vector Shape - Group","hd":false},{"ty":"st","c":{"a":0,"k":[0.419607843137,0.427450980392,0.501960784314,1],"ix":3},"o":{"a":0,"k":100,"ix":4},"w":{"a":0,"k":0,"ix":5},"lc":1,"lj":1,"ml":4,"bm":0,"nm":"Stroke 1","mn":"ADBE Vector Graphic - Stroke","hd":false},{"ty":"fl","c":{"a":0,"k":[0.188235309077,0.20000001496,0.270588235294,1],"ix":4},"o":{"a":0,"k":100,"ix":5},"r":1,"bm":0,"nm":"Fill 1","mn":"ADBE Vector Graphic - Fill","hd":false},{"ty":"tr","p":{"a":1,"k":[{"i":{"x":0,"y":1},"o":{"x":0.068,"y":0},"t":34,"s":[1.361,136.127],"to":[0,0],"ti":[0,0]},{"i":{"x":0.194,"y":1},"o":{"x":0.979,"y":0},"t":51,"s":[1.361,153.127],"to":[0,0],"ti":[0,0]},{"i":{"x":0.361,"y":1},"o":{"x":0.802,"y":0},"t":64,"s":[1.361,32.127],"to":[0,0],"ti":[0,0]},{"i":{"x":0.022,"y":1},"o":{"x":0.392,"y":0},"t":81,"s":[1.361,141.127],"to":[0,0],"ti":[0,0]},{"t":90,"s":[1.361,136.127]}],"ix":2},"a":{"a":0,"k":[1.361,135.127],"ix":1},"s":{"a":1,"k":[{"i":{"x":[0,0],"y":[1,1]},"o":{"x":[0.068,0.068],"y":[0,0]},"t":34,"s":[100,100]},{"i":{"x":[0.194,0.194],"y":[1,1]},"o":{"x":[0.979,0.979],"y":[0,0]},"t":51,"s":[136,74]},{"i":{"x":[0.361,0.361],"y":[1,1]},"o":{"x":[0.802,0.802],"y":[0,0]},"t":64,"s":[81,129]},{"i":{"x":[0.022,0.022],"y":[1,1]},"o":{"x":[0.392,0.392],"y":[0,0]},"t":81,"s":[115,85]},{"t":90,"s":[100,100]}],"ix":3},"r":{"a":0,"k":0,"ix":6},"o":{"a":0,"k":100,"ix":7},"sk":{"a":0,"k":0,"ix":4},"sa":{"a":0,"k":0,"ix":5},"nm":"Transform"}],"nm":"Shape 1","np":4,"cix":2,"bm":0,"ix":2,"mn":"ADBE Vector Group","hd":false}],"ip":0,"op":600,"st":0,"ct":1,"bm":0},{"ddd":0,"ind":4,"ty":4,"nm":"mask","parent":8,"td":1,"sr":1,"ks":{"o":{"a":0,"k":100,"ix":11},"r":{"a":0,"k":0,"ix":10},"p":{"a":0,"k":[-59.498,-403,0],"ix":2,"l":2},"a":{"a":0,"k":[254.502,-270,0],"ix":1,"l":2},"s":{"a":1,"k":[{"i":{"x":[0.667,0.667,0.667],"y":[1,1,1]},"o":{"x":[0.333,0.333,0.333],"y":[0,0,0]},"t":90,"s":[100,100,100]},{"t":100,"s":[354,354,100]}],"ix":6,"l":2}},"ao":0,"shapes":[{"ty":"gr","it":[{"d":1,"ty":"el","s":{"a":0,"k":[205.004,205.004],"ix":2},"p":{"a":0,"k":[0,0],"ix":3},"nm":"Ellipse circuit 1","mn":"ADBE Vector Shape - Ellipse","hd":false},{"ty":"st","c":{"a":0,"k":[0.027450982262,0.027450982262,0.027450982262,1],"ix":3},"o":{"a":0,"k":100,"ix":4},"w":{"a":0,"k":0,"ix":5},"lc":1,"lj":1,"ml":4,"bm":0,"nm":"Circuit 1","mn":"ADBE Vector Graphic - Stroke","hd":false},{"ty":"fl","c":{"a":0,"k":[0.027450982262,0.027450982262,0.027450982262,1],"ix":4},"o":{"a":0,"k":100,"ix":5},"r":1,"bm":0,"nm":"Fill 1","mn":"ADBE Vector Graphic - Fill","hd":false},{"ty":"tr","p":{"a":0,"k":[254.502,-167.498],"ix":2},"a":{"a":0,"k":[0,0],"ix":1},"s":{"a":0,"k":[100,100],"ix":3},"r":{"a":0,"k":0,"ix":6},"o":{"a":0,"k":100,"ix":7},"sk":{"a":0,"k":0,"ix":4},"sa":{"a":0,"k":0,"ix":5},"nm":"Transform"}],"nm":"Ellipsis 1","np":3,"cix":2,"bm":0,"ix":1,"mn":"ADBE Vector Group","hd":false}],"ip":0,"op":654,"st":54,"ct":1,"bm":0},{"ddd":0,"ind":8,"ty":3,"nm":"Null 7","sr":1,"ks":{"o":{"a":0,"k":0,"ix":11},"r":{"a":0,"k":0,"ix":10},"p":{"a":0,"k":[313,259,0],"ix":2,"l":2},"a":{"a":0,"k":[0,0,0],"ix":1,"l":2},"s":{"a":0,"k":[100,100,100],"ix":6,"l":2}},"ao":0,"ip":0,"op":600,"st":0,"bm":0}],"markers":[],"props":{}}